{
    "last_update": "2026-05-29 18:49:39",
    "market_index": {
        "taiex": {
            "price": 44732.94,
            "change": 1096.5,
            "percent": 2.51
        },
        "nasdaq": {
            "price": 26917.47,
            "change": 242.74,
            "percent": 0.91
        },
        "tsm_adr": {
            "price": 424.86,
            "change": 2.13,
            "percent": 0.5
        },
        "sox": {
            "price": 12829.14,
            "change": 126.95,
            "percent": 1.0
        },
        "dji": {
            "price": 50668.97,
            "change": 24.69,
            "percent": 0.05
        },
        "tx": {
            "price": 44732.94,
            "change": 1096.5,
            "percent": 2.51
        }
    },
    "chips": {
        "foreign_futures_net": -25600,
        "retail_ratio": 12.5,
        "institutional_buying": {
            "foreign": -120.5,
            "itc": 45.2,
            "dealer": -12.3
        }
    },
    "strategy_positions": [
        {
            "code": "TXF1!",
            "name": "45分鐘SP策略 (做空 📉)",
            "buy_price": 41669.0,
            "buy_time": "2026-05-22 02:55:19",
            "pnl_percent": 0.0,
            "tp_price": 41489.0,
            "sl_price": 41789.0,
            "is_closed": false,
            "direction": "sell"
        },
        {
            "code": "TMF01",
            "name": "極速測試 (做多 📈)",
            "buy_price": 42678.0,
            "buy_time": "2026-05-22 23:57:04",
            "pnl_percent": 0.0,
            "tp_price": 42858.0,
            "sl_price": 42558.0,
            "is_closed": false,
            "direction": "buy"
        }
    ]
}